{
  "activity" : [ {
    "troupeName" : "銀河谷音劇團",
    "hallType" : "中壢藝術館",
    "hallSelect" : "音樂廳",
    "performanceType" : "表演類",
    "performanceSelect" : "親子",
    "title" : "銀河谷音劇團《國王的新衣》",
    "content" : "愛穿新衣的國王找來兩位裁縫師縫製新衣， 他們向國王保證能夠織出這世界上 最美麗與奇特的布，並將它做成衣服。 最特別的是， 有智慧的人和努力工作的人才看得見! 國王一聽心花怒放，花了大筆的錢來 製作這件前所未有的「天衣」。 遊行的日子終於來到， 大家都擠在街上要看國王的新衣。  但是，國王的身上，竟然什麼都沒有......",
    "performanceTimeInfo" : "12/31(五) 14:30",
    "url" : "",
    "admissionWay" : "售票",
    "admissionInfo" : "OPENTIX售票：300、400、500、600、800、1000、1200",
    "admissionNumber" : "",
    "admissionDate" : "",
    "handicap" : "",
    "publishDate" : "2021/12/02 10:16 上午",
    "performanceDate" : [ "2021/12/31 02:30 下午~2021/12/31 04:30 下午" ],
    "pic" : [ "https://www.afmc.gov.tw/Upload/2021120210161434c2fa0.png" ],
    "hashCode" : "2000583786"
  }, {
    "troupeName" : "相聲瓦舍",
    "hallType" : "中壢藝術館",
    "hallSelect" : "音樂廳",
    "performanceType" : "表演類",
    "performanceSelect" : "戲劇",
    "title" : "相聲瓦舍《三十三》",
    "content" : "白居易出現購物頻道，聯名贊助除毛膏？！\n楊慎原來是阿卡貝拉的先驅，一首《臨江仙》，Hold住全場。\n王勃才是預言神童，「天涯若比鄰」網路零距離？！\n古人以日常作詩、瓦舍以幽默做戲。\n\n【相聲瓦舍】挑選經典古詩韻文，捧逗成每首3分鐘段子搬上舞台。\n後疫情時期，瓦舍將持續演出 《三十三》，用愉快的心情陪伴大家回歸日常。",
    "performanceTimeInfo" : "12/25(六)14:30",
    "url" : "",
    "admissionWay" : "售票",
    "admissionInfo" : "OPENTIX:500 、 800 、 1,000 、 1,200 、 1,500 、 1,800",
    "admissionNumber" : "",
    "admissionDate" : "",
    "handicap" : "",
    "publishDate" : "2021/11/24 02:51 下午",
    "performanceDate" : [ "2021/12/25 02:30 下午~2021/12/25 05:00 下午" ],
    "pic" : [ "https://www.afmc.gov.tw/Upload/2021112414535419ec180.png", "https://www.afmc.gov.tw/Upload/202111241453127490fb0.png" ],
    "hashCode" : "466319950"
  }, {
    "troupeName" : "武陵高中音樂班管弦樂團",
    "hallType" : "中壢藝術館",
    "hallSelect" : "音樂廳",
    "performanceType" : "表演類",
    "performanceSelect" : "音樂",
    "title" : "2021 武陵高中年度協奏曲音樂會",
    "content" : "本次音樂會將演出鋼琴、雙簧管、大提琴等經典協奏曲曲目,並以貝多芬第九號交響曲來展現氣勢滂礡的全國冠軍樂團,帶給您震撼的音樂饗宴。\n演出曲目\nFranz Liszt / Totentanz\nPyotr IlyichTchaikovsky / Variations on a Rococo Theme\nLudwig Van Beethoven / Symphony No.9 in D minor, Op. 125, \"Choral\" –\n1 st. &2nd movement.\n指揮:庾燕誠 教授\n獨奏者:陳昱錡  林宥華",
    "performanceTimeInfo" : "12/30(四)19:30",
    "url" : "",
    "admissionWay" : "索票",
    "admissionInfo" : "索票請洽03-3698170分機250武陵高中",
    "admissionNumber" : "",
    "admissionDate" : "2021-12-10T09:00:00",
    "handicap" : "",
    "publishDate" : "2021/11/24 03:05 下午",
    "performanceDate" : [ "2021/12/30 07:30 下午~2021/12/30 09:30 下午" ],
    "pic" : [ "https://www.afmc.gov.tw/Upload/2021112415055504cc9b0.png" ],
    "hashCode" : "1040472086"
  }, {
    "troupeName" : "表演工作坊",
    "hallType" : "桃園展演中心",
    "hallSelect" : "展演廳",
    "performanceType" : "表演類",
    "performanceSelect" : "戲劇",
    "title" : "表演工作坊《絕不付帳！》",
    "content" : "當諾貝爾文學獎得主碰到台灣歐巴桑拒絕買單……\n【表坊】經典再現！\n一群家庭主婦的革命長什麼樣子？不滿物價不斷上漲，辛苦扛貸款的房子居然是豆腐渣工程，日子難過而奸商卻吃香喝辣，為了保護自己的家園，她們決定採取猛烈的行動！\n\n她們大喊：絕不付帳！絕不付帳！\n\n而女主角的先生剛好是一位奉公守法的人士，不可能原諒太太去搶超市這種事。一地的贓物，眼看先生就要回家，怎麼辦？這群手無寸鐵的老百姓只好把自己的肚子「搞大」，一夕之間，鄰居太太、隔壁小狗、連小學生都挺著大肚子滿街跑……",
    "performanceTimeInfo" : "4/9 (六)     19:30",
    "url" : "https://youtu.be/Vl7VtZSdMDo",
    "admissionWay" : "售票",
    "admissionInfo" : "OPENTIX兩廳院生活文化售票系統\n票價：$600、$900、$1200、$1600、$2000、$2500、$3000",
    "admissionNumber" : "",
    "admissionDate" : "",
    "handicap" : "",
    "publishDate" : "2021/11/19 03:01 下午",
    "performanceDate" : [ "2022/04/09 07:30 下午~2022/04/09 10:00 下午" ],
    "pic" : [ "https://www.afmc.gov.tw/Upload/202111191503428a93220.png", "https://www.afmc.gov.tw/Upload/20211119150393041da60.png", "https://www.afmc.gov.tw/Upload/202111191503843f554d0.png", "https://www.afmc.gov.tw/Upload/20211119150334199d700.png" ],
    "hashCode" : "1922306563"
  }, {
    "troupeName" : "桃園市立桃園高級中等學校舞蹈班",
    "hallType" : "桃園展演中心",
    "hallSelect" : "展演廳",
    "performanceType" : "表演類",
    "performanceSelect" : "舞蹈",
    "title" : "桃園市立桃園高級中等學校舞蹈班第27屆畢業舞展《以舞相聚》",
    "content" : "\"桃園高中舞蹈班每年的畢業舞展，都吸引許多喜愛表演藝術的觀眾前來觀賞，藉由這樣的表演，讓更多人了解舞蹈藝術的豐富與動人。本屆舞展演出的作品早在半年前即開始籌劃。為將最完美的成果呈現在觀眾眼前，學生反覆練習、揮灑汗水，不只是為了要求個人動作的熟練精準，更為了培養團隊絕佳的默契。\n當然，這一切的努力，最期盼的就是您屆時前往與我們共度美好的夜晚。您熱情的掌聲，將是我們繼續努力的動力。期待您的蒞臨!\n\"",
    "performanceTimeInfo" : "12月17日(五)19:30",
    "url" : "",
    "admissionWay" : "索票",
    "admissionInfo" : "洽詢單位/電話：桃園高中註冊組(請親自登記索票，一人限索2張)/03-3946001分機6135、6216",
    "admissionNumber" : "2",
    "admissionDate" : "",
    "handicap" : "",
    "publishDate" : "2021/11/19 04:43 下午",
    "performanceDate" : [ "2021/12/17 07:30 下午~2021/12/17 09:00 下午", "2021/12/17 02:30 下午~2021/12/17 04:00 下午" ],
    "pic" : [ "https://www.afmc.gov.tw/Upload/202111191643637d9f2a0.png" ],
    "hashCode" : "1993207063"
  }, {
    "troupeName" : "星空交響管樂團",
    "hallType" : "中壢藝術館",
    "hallSelect" : "音樂廳",
    "performanceType" : "表演類",
    "performanceSelect" : "音樂",
    "title" : "星空交響管樂團「狂樂動漫魂-第七彈」",
    "content" : "聖誕節前夕，動漫迷必參加星空交響管樂團《狂樂動漫魂》動漫音樂會於12月19日星期日中壢藝術館今年開唱至第七彈啦！有超熱血動漫歌手Ａ拔帶來咒術迴戰『迴迴奇譚』、進擊的巨人『僕の戦争』以及哆啦Ａ夢劇場版-大雄的宇宙小戰爭『Universe』，當然超人氣動漫歌手CHIA 及 某某人帶來，年度最火紅鬼滅之刃『竈門炭治郎のうた』、與哆拉Ａ夢動畫版Stand by me 2『虹』、ＪＯＪＯ迷因神曲『il Vento D'oro Overture』及小林家的龍女僕『愛のシュプリーム",
    "performanceTimeInfo" : "12/19(日)19:00",
    "url" : "",
    "admissionWay" : "售票",
    "admissionInfo" : "OPENTIX:400 、 500 、 800 、 1,000",
    "admissionNumber" : "",
    "admissionDate" : "",
    "handicap" : "",
    "publishDate" : "2021/11/24 02:44 下午",
    "performanceDate" : [ "2021/12/19 07:00 下午~2021/12/19 10:00 下午" ],
    "pic" : [ "https://www.afmc.gov.tw/Upload/202111241444648fd4320.png", "https://www.afmc.gov.tw/Upload/202111241444345a649d0.png", "https://www.afmc.gov.tw/Upload/202111241444257cfebc0.png" ],
    "hashCode" : "915726474"
  }, {
    "troupeName" : "蘭陽戲劇團",
    "hallType" : "桃園展演中心",
    "hallSelect" : "展演廳",
    "performanceType" : "表演類",
    "performanceSelect" : "戲劇",
    "title" : "蘭陽戲劇團「2021年歌仔戲推廣計畫- 戲曲行腳。人情味」",
    "content" : "《浮沉紗帽》\n代天巡狩崢嶸少年崔雲龍，一日出巡至子虛府烏有縣，卻不見遭其貶職之縣令鄭則清前來侍候，崔爲打聽鄭之官聲，而鄭爲查探一命案，未曾謀面之兩人不期而遇於一茶坊。初時彼此狐疑對方，繼而慢慢相惜，並合力査得艾春蘭竟是通奸害夫。\n作賊喊捉賊，兇手乃金知府外甥劉強。劉被引蛇出洞，鄭率崔等圍捕但仍被逃脫。崔順從鄭夫妻美意留衙當差，並權代因公受傷之鄭審案，卻又無故私放犯婦，天子學生成了階下囚。鄭夫妻前來探監崔猶強辯，其實已心知肚鄭明錯貶了鄭，待鄭緝得劉強判處極刑，金知府闖堂干預，劉艾見機翻案，反控鄭奸淫寡婦，曲判良民，崔猶做不利鄭之曖昧證詞以試探金等一干羽黨反應，一連串之苦肉記，看穿了清濁賢愚，崔乃及時表明身份，替鄭解圍，復其官職，並嚴懲奸官庸吏，提振朝廷紀綱。",
    "performanceTimeInfo" : "12月19日(日)14:30",
    "url" : "",
    "admissionWay" : "索票",
    "admissionInfo" : "索票入場",
    "admissionNumber" : "",
    "admissionDate" : "",
    "handicap" : "",
    "publishDate" : "2021/11/19 04:35 下午",
    "performanceDate" : [ "2021/12/19 02:30 下午~2021/12/19 04:30 下午" ],
    "pic" : [ "https://www.afmc.gov.tw/Upload/2021111916359990bf5c0.png" ],
    "hashCode" : "718068390"
  }, {
    "troupeName" : "永平工商表演藝術科",
    "hallType" : "桃園展演中心",
    "hallSelect" : "展演廳",
    "performanceType" : "表演類",
    "performanceSelect" : "其他",
    "title" : "藝憶翼",
    "content" : "永平工商表演藝術科第九屆畢業展\n主題：藝憶翼\n內容：本次節目演出內容分為三個段落：\n【藝】.結合表演藝術科實習課程及業師指導，將舞蹈、音樂、戲劇三大藝術編排成精華作品\n【憶】.以回憶為主軸由學生創作及編劇的歌舞劇形式演出\n【翼】.意指祝福應屆畢業生未來能順利走向美好人生，以學生創作畢業歌曲，及學生編排團體謝幕舞蹈呈現，感謝父母栽培、感動三年的校園生活、精彩未來的美好前程！",
    "performanceTimeInfo" : "12月22日(三)19:00",
    "url" : "",
    "admissionWay" : "索票",
    "admissionInfo" : "索票進場，\n索票資訊請洽詢永平工商表演藝術科",
    "admissionNumber" : "",
    "admissionDate" : "",
    "handicap" : "",
    "publishDate" : "2021/11/19 04:47 下午",
    "performanceDate" : [ "2021/12/22 07:00 下午~2021/12/22 10:00 下午" ],
    "pic" : [ "https://www.afmc.gov.tw/Upload/2021111916475070f99b0.png", "https://www.afmc.gov.tw/Upload/202111191647758b7ae70.png" ],
    "hashCode" : "2015023606"
  }, {
    "troupeName" : "米豆",
    "hallType" : "A8藝文中心",
    "hallSelect" : "展覽空間",
    "performanceType" : "表演類",
    "performanceSelect" : "講座",
    "title" : "【從故事到地球－零浪費的衛生紙套】",
    "content" : "愛護我們這塊土地，只需要一點小小的不一樣，就有機會造成大大的不同！延續零浪費雜貨店永續經營的概念，也希望從街坊和生活做起，每個人都可以為自己生活的地方做點什麼。特別邀請到米豆老師分享衛生紙套和手機套的製作，捨棄多餘的包裝，你我都可以簡單踏入無塑生活！",
    "performanceTimeInfo" : "12/18 14:00-15:30",
    "url" : "http://www.a8artcenter.com.tw/signup.php?utm_source=afmc&utm_medium=event",
    "admissionWay" : "自由入場",
    "admissionInfo" : "酌收材料費，請事先至A8藝文中心官方網站(http://www.a8artcenter.com.tw/signup.php?utm_source=afmc&utm_medium=event)報名。",
    "admissionNumber" : "",
    "admissionDate" : "",
    "handicap" : "",
    "publishDate" : "2021/11/23 07:40 下午",
    "performanceDate" : [ "2021/12/18 02:00 下午~2021/12/18 03:30 下午" ],
    "pic" : [ "https://www.afmc.gov.tw/Upload/2021112319439663a5240.png" ],
    "hashCode" : "1120553856"
  }, {
    "troupeName" : "果陀劇場",
    "hallType" : "桃園展演中心",
    "hallSelect" : "展演廳",
    "performanceType" : "表演類",
    "performanceSelect" : "戲劇",
    "title" : "果陀劇場 人性機智喜劇 《ART》",
    "content" : "你有沒有朋友？我是說「真正的朋友」\n你在朋友眼中是什麼樣子？\n\n2016年場場完售\n2018加演再度秒殺 一票難求\n2021年魅力席捲全台\n\n一齣令人讚嘆不已、幽默嘲諷有發人深省的絕妙好戲\n卜學亮、屈中恆、曾國城 超強鐵三角組合\n\n\n《ART》故事中三位性格各異、卻是數十年交情的好朋友，因其中一人買了一幅「畫著白色斜線的白色油畫」引發了一場出人意料的唇槍舌戰，他們挑戰彼此的價值觀，機智、幽默且諷刺的對白，編織出細緻複雜的人性，充滿爭辯與歡笑。劇中細膩刻劃男人之間情感的奇妙變化和差距，多年情誼看似堅固，有時卻脆弱的難以想像，將角色人格的軟弱、固執表現淋漓盡致。",
    "performanceTimeInfo" : "9/2  （五）19:30\n9/3  （六）14:30\n",
    "url" : "https://tixfun.com/UTK0201_?PRODUCT_ID=N11RWHAT",
    "admissionWay" : "售票",
    "admissionInfo" : "TixFun售票網，票價：500、900、1400、1700、2000、2300、2600元\n\n\n★★配合中央防疫政策， 並顧及疫情未平群聚之不安， 《ART》延期演出。★★\n\n延期場次： \n2021/6/12(六)19:30→2022/9/2(五)19:30 \n2021/6/13(日)14:30→2022/9/3(六)14:30\n\n已購票的觀眾請持原票券入座新場次，不需換票。\n為感謝您的支持，果陀劇場誠心準備\n【因為有您，一起走過疫情小紀念品】\n與您明年劇場相見。\n\n若持票觀眾不便觀賞新的場次，\n請於2021/7/12(一)前洽原購票單位辦理，免收手續費。\n\n衷心感謝已購票觀眾， 於此疫情期間仍繼續支持果陀劇場。 期盼大家平安健康，疫情早日結束！\n\n若有任何疑問，請洽果陀劇場：02-87721867 或TixFun售票系統客服中心：02-27073053 詳情請上果陀劇場粉絲專頁查詢",
    "admissionNumber" : "",
    "admissionDate" : "",
    "handicap" : "",
    "publishDate" : "2021/04/13 09:59 上午",
    "performanceDate" : [ "2022/09/02 07:30 下午~2022/09/02 05:30 下午" ],
    "pic" : [ "https://www.afmc.gov.tw/Upload/202105261747537f3e220.png" ],
    "hashCode" : "179317546"
  }, {
    "troupeName" : "告五人、拍謝少年、入選團隊",
    "hallType" : "桃園陽光劇場",
    "hallSelect" : "桃園陽光劇場",
    "performanceType" : "表演類",
    "performanceSelect" : "音樂",
    "title" : "2021鐵玫瑰熱音賞決賽",
    "content" : "桃園鐵玫瑰熱音賞以培養在地樂團為宗旨，分校園組及社會組競賽，經初賽晉選的團隊，將透過完整系統化培訓課程後，進入決賽，總獎金高達150萬元，期待發掘培育更多優秀樂壇新秀，達到鼓勵臺灣多元創作及提升音樂素質之目的。",
    "performanceTimeInfo" : "110年12月11日（星期六）下午2：00-7：00\n110年12月12日（星期日）下午2：00-7：00",
    "url" : "",
    "admissionWay" : "自由入場",
    "admissionInfo" : "自由入場",
    "admissionNumber" : "",
    "admissionDate" : "",
    "handicap" : "",
    "publishDate" : "2021/12/07 05:04 下午",
    "performanceDate" : [ "2021/12/11 08:00 上午~2021/12/11 10:00 下午", "2021/12/12 08:00 上午~2021/12/12 10:00 下午" ],
    "pic" : [ "https://www.afmc.gov.tw/Upload/202112071704747b44160.png" ],
    "hashCode" : "563527914"
  }, {
    "troupeName" : "故事工廠",
    "hallType" : "桃園展演中心",
    "hallSelect" : "展演廳",
    "performanceType" : "表演類",
    "performanceSelect" : "戲劇",
    "title" : "故事工廠《我們與惡的距離》全民公投劇場版",
    "content" : "【你自以為是的正義，可能把另一個人推向地獄。】\n在戲院犯下無差別殺人案的兇手；想尋求公道的被害者父母；試圖撕下「殺人魔家人」標籤的加害者家屬；被視為「魔鬼代言人」的人權律師，究竟誰是善？誰是惡？輿論就是一場社會公審，「你」就是擁有投票權的「輿論」，2次公投將導向4個不同的結局，你的一票也許能阻止下一場悲劇的發生。\n來看看精彩片段：https://youtu.be/lFBQsvDOz5A\n\n改編自公共電視文化事業基金會連續劇《我們與惡的距離》\n原著｜呂蒔媛\n編導｜黃致凱\n演員｜尹馨、狄志杰、謝瓊煖、吳定謙、房思瑜、李紹祥、吳怡霈、陳以恩、李劭婕、李右杭、劉珊珊、郭耀仁、楊銘威、楊迦恩、邱彥翔、林木森、黃士勛、劉桓、劉嘯榮、林宥彤\n\n\n\n\n1.首演完售｜《我們與惡的距離》全民公投劇場版 2021好評加演\nhttps://wenk.in/SW00YINR\n\n\n2.《我們與惡的距離》全民公投劇場版人權律師王赦 信念與現實的掙扎！\nhttps://wenk.in/SW00ckKG\n\n\n3.好評沒有距離｜《我們與惡的距離》全民公投劇場版 2021好評加演\nhttps://wenk.in/SW00eB31\n\n\n4.正義的代價｜《我們與惡的距離》全民公投劇場版 2021二度加演\nhttps://wenk.in/SW00mWxl",
    "performanceTimeInfo" : "12/26 (日)   14:30  ",
    "url" : "https://wenk.in/SW00mWxl",
    "admissionWay" : "售票",
    "admissionInfo" : "購票通路：TixFun售票系統、7-11皆可購票\n2500/2200/1800/1500/1200/900/700/500",
    "admissionNumber" : "",
    "admissionDate" : "",
    "handicap" : "",
    "publishDate" : "2021/07/02 09:53 上午",
    "performanceDate" : [ "2021/12/26 02:30 下午~2021/12/26 05:30 下午" ],
    "pic" : [ "https://www.afmc.gov.tw/Upload/202107021002831b960e0.png", "https://www.afmc.gov.tw/Upload/202107021001238375970.png", "https://www.afmc.gov.tw/Upload/202107020953798f9cc40.png", "https://www.afmc.gov.tw/Upload/202107021002545a8ee40.png" ],
    "hashCode" : "2070062844"
  }, {
    "troupeName" : "漢霖民俗說唱藝術團",
    "hallType" : "桃園展演中心",
    "hallSelect" : "展演廳",
    "performanceType" : "表演類",
    "performanceSelect" : "戲劇",
    "title" : "【演出延期】漢霖民俗說唱藝術團《再造經典－新十項全能》",
    "content" : "110年漢霖特別規劃《再造經典－新十項全能》公演，由王振全團長挑選經典的劇種及作品，領軍漢霖新藝輩演員來演出，讓說唱藝術能夠生生不息，傳統節目也能風華再現，同時給漢霖的新藝輩團員留下示範，接觸這些已經失傳的曲種，學習並再造，傳承說唱藝術的文化。\n\n漢霖民俗說唱藝術團成立迄今已有35年的歷史，為國內第一個專業說唱藝術團體。年年固定公演，至今製作演出已逾九千場，創作編寫相聲數百段，演出足跡遍達全球五大洲六十七個國家，臺灣寶島數百個鄉鎮市。薪傳無數，舉凡國內傑出中青輩說唱菁英無一不經「漢家甘霖」之孕育。\n\n「漢霖」以發掘、研習、引進、展演、推廣、教育、傳承、培植人才到專業演員、再造說唱藝術為己任，從無到有，從有到精。將說唱藝術在臺灣原本僅有相聲、京韻大鼓、數來寶、雙黃、山東快書、河南墜子、說書講古共七種，從無到有的發展出「竹板快書」、「太平歌詞」、「八角鼓」、「單弦」、「滑稽大鼓」、「梅花大鼓」、「西河大鼓」「喜劇小品」、「四川打連廂」、「連珠快書」、「評書」、「玉板書」、「樂亭大鼓」、「奉天大鼓」等共二十九個曲種，「相聲」則由僅有的「相聲集錦」16卷錄音，豐富至1123段，繁榮了寶島臺灣的說唱內涵。邇來，更成立了【漢霖說唱藝術圖書館】，並開創國、台、客、英四語相聲，首創【漢霖相聲茶館】，屬國內歷久不衰的說唱之家。\n\n節目簡介\n（一）說書：諸葛亮舌戰群儒\n書用說的比用看的更容易讓人理解吸收之外，說書的情境渲染力也比讀者自行想像來的更強，因此好的說書除了需要語言的情緒表達足夠震撼觀眾，也需要對文章有一定的理解力，才能將故事的內容完整告訴觀眾們。說書的技巧延伸了許多技藝的發揮，如竹板快書、拉洋片等，可說是說書改良發揮的多元形式，因此無論在哪個時代，說書一直都具有極大的影響力。此段故事講述諸葛亮為聯盟孫權抵抗曹操的過程中遭到東吳諸謀士的責難，最後都被諸葛亮一一反駁，啞口無言，是一段精采絕倫的辯論大會！\n\n（二）群口相聲：名師出高徒\n由傳統相聲「訓徒」衍生而來。師道，傳道、授業、解惑也，萬不可為人師表卻不學無術而誤人子弟。「訓徒」是先民留下來幽默寶庫裡的瑰寶，千錘百鍊、去蕪存菁，仍然在現今人人喜聞樂見，自有它不朽價值。\n\n（三）單口相聲：歪批流行歌曲\n1993年，行政院陸委會主辦「中華友好說唱藝術訪問團」，邀請國內八個說唱藝術團共組赴陸交流公演，王振全團長以當時自創的單口相聲《歪批流行歌曲》在大陸相聲界掀起旋風，他將詮釋歌星唱腔不同的角度以及時下流行歌曲的歪歌版，以此段記錄及關心流行熱潮的新新人類，是王團長單口相聲的代表作品！\n\n（四）竹板快書：孫悟空三打白骨精\n竹板快書原稱快板書，民國75年由本團從大陸引進並定名，從此在臺灣生根發芽。相對相聲而言，竹板快書節奏鮮明，爽朗輕快。表演者手持竹板，敲奏輕脆音響，唸白配合節拍，念唱古書或軼事。三打白骨精說的是，唐僧他到西天去取經，一路上，師徒四人拔山涉水的趕路程，路程中孫悟空三次識破白骨精法術的故事，為竹板快書的經典大段。\n\n（五）鐵板快書：老張下棋打瘸猴\n「鐵板快書」可說是三百四十一種說唱藝術裡最為獨特的一門曲藝，表演者以兩塊半月形的銅板或鐵板擊節唱唸，在臺灣屬罕見曲藝，獨本團團長王振全先生擅之。本段因應臺灣觀眾口味所發展出來的一段新時代鐵板快書，對年輕一輩的朋友來說，也是相當具有吸引人的。\n\n（六）太平歌詞：五龍捧聖\n「太平歌詞」流行於平、津的曲種，內容多為歌頌太平盛世勸人為善或趣事。演唱者手持玉子板擊節清唱，佐以身段動作表演。唱腔樸素簡單，多為念誦，僅在句末搭上唱詞。本段敘述屠夫欲宰家中大母豬宴客時，五隻豬仔哭求屠夫刀下留母，深具教化人心意義，教人孝順之道，且聽五豬如何使屠夫回心轉意。\n\n（七）京韻大鼓：劍閣聞鈴\n《劍閣聞鈴》是一篇優美動人的抒情詩，原名《憶真妃》。本詩描寫唐玄宗避安史之亂，唐明皇在馬嵬坡賜死楊玉環以後，繼續入蜀。西行途中夜宿劍閣，在冷雨淒風伴隨叮咚作響的簷鈴聲中，思念慘死馬嵬坡的愛妃楊玉環，一夜未眠到天明的情景。聞王振全團長說，在臺灣能夠演藝這段的演員，還不知道有沒有超過三位呢？\n\n（八）岔曲：八花八典\n“八角鼓”是清朝乾隆年間，雲桂總督阿桂平大小金川之亂而產生的，“岔曲”是清代流行的曲種，其“八角鼓”的八角，暗示八旗﹙正黃、鑲黃、正白、鑲白、正紅、鑲紅、正藍、鑲藍﹚的意思，鼓下方所系的穗帶，一為黃色，一為杏黃色，意思是左右兩翼，“八角鼓”沒有柄把，取意為永罷干戈。通常開場搭配單弦﹙單弦曲種名也叫八角鼓、或合稱單弦八角鼓﹚，表演開始首唱“岔曲”，通常內容雅致，篇幅不大，是為小品。八花八典唱的是八種花的八個典故，有蘭花、海棠、菊花、桂花、蓮花、桃花、梅花、牡丹。\n\n（九）牛骨數來寶：升棺發財\n大玩文字遊戲的嘻哈音樂Hip-hop也叫rap、饒舌音樂，也譯為說唱音樂。而說唱藝術也有著類似的曲種，那就是繞口令、數來寶，同樣都是玩文字遊戲和押韻技巧，在難度上傳統藝術可不輸給嘻哈音樂，更需講究語言的字正音清。此段由王振全團長手持繫以銅鈴的牛跨骨搭配漢霖捧哏大師趙中興，唱給觀眾聽屬於中國的饒舌藝術！\n\n（十）對口相聲：地理圖\n對口相聲中常見的表現形式，也叫\"背口\"。\"貫口\"的\"貫\"字，是一氣呵成，一貫到底的意思，講究語言的快而不亂、慢而不斷、高而不喧、低而不啞…。常見的段子如《報菜名》《八扇屏》《白事會》都含有大段的貫口。貫口分為大貫兒和小貫兒兩種。大貫兒一般上百句，小貫兒一般十幾句到幾十句不等，而《報菜名》與《地理圖》並稱為兩大貫兒，為貫口相聲的經典大段。\n\n\n\n★★   109年8月在淡水圖書館的演出      https://youtu.be/kQB5wHsiOQM",
    "performanceTimeInfo" : "原  7/23(五)   19:30   延至  12/14  (二)   19:30  演出",
    "url" : "https://www.opentix.life/event/1400658466756866053",
    "admissionWay" : "售票",
    "admissionInfo" : "opentix兩廳院售票系統：均一票價200\n\n因應疫情升溫，三級警戒延長至6月28日，為顧及疫情未平群聚之不安，原定7/23（五）19:30於桃園展演中心舉辦的《再造經典－新十項全能》活動延期至12/14（二）19:30。\n已購票的觀眾請保留票券，可於12/14當日使用，我們將盡最大努力，維護您的權益不受損失。\n\n造成大家的不便，敬請見諒；疫情期間，也請大家務必落實各種防疫措施，保護自己也保護他人！期盼大家平安健康，疫情早日結束！\n\n若有任何疑問，請洽漢霖民俗說唱藝術團：02-82301910 / 82301912 \n或請上漢霖粉絲專頁查詢：https://www.facebook.com/happyhanlin",
    "admissionNumber" : "",
    "admissionDate" : "",
    "handicap" : "",
    "publishDate" : "2021/05/17 04:27 下午",
    "performanceDate" : [ "2021/12/14 07:30 下午~2021/12/14 09:30 下午" ],
    "pic" : [ "https://www.afmc.gov.tw/Upload/2021062911242411b2e30.png", "https://www.afmc.gov.tw/Upload/2021110913351921c00d0.png" ],
    "hashCode" : "1810130011"
  }, {
    "troupeName" : "內壢國中音樂班",
    "hallType" : "中壢藝術館",
    "hallSelect" : "音樂廳",
    "performanceType" : "表演類",
    "performanceSelect" : "音樂",
    "title" : "內壢國中音樂班畢業音樂會暨成果發表會",
    "content" : "本次將演奏多位作曲家所創作的管樂作品，包含古典與流行等音樂風格，結合獨奏、重奏、合奏等展演類型，呈現學生三年來的學習成果。",
    "performanceTimeInfo" : "12/29(三)19:00",
    "url" : "",
    "admissionWay" : "自由入場",
    "admissionInfo" : "",
    "admissionNumber" : "",
    "admissionDate" : "",
    "handicap" : "",
    "publishDate" : "2021/11/24 03:02 下午",
    "performanceDate" : [ "2021/12/29 07:00 下午~2021/12/29 09:00 下午" ],
    "pic" : [ "https://www.afmc.gov.tw/Upload/202111241502047f19b60.png" ],
    "hashCode" : "1619454838"
  }, {
    "troupeName" : "福爾摩沙合唱團、幕聲合唱團、武陵人合唱團",
    "hallType" : "中壢藝術館",
    "hallSelect" : "音樂廳",
    "performanceType" : "表演類",
    "performanceSelect" : "音樂",
    "title" : "2021桃園合唱藝術節閉幕音樂會-經典人聲(合唱)之夜",
    "content" : "「2021桃園合唱藝術節」集結過去經驗與主軸，持續展望國際並深耕在地，閉幕音樂會以「經典人聲」為主題，由2019桃樂獎得獎團「武陵人合唱團」擔任開場演唱團隊，特別邀請享譽國際的「福爾摩沙合唱團」、臺灣最知名的女聲團隊「幕聲合唱團」擔綱演出；同日揭曉的「2021桃園合唱藝術節合唱大賽」冠軍團隊，也將於閉幕音樂會當中獻藝。",
    "performanceTimeInfo" : "12/12(日)19:30",
    "url" : "https://vfty.org/concert-close",
    "admissionWay" : "索票",
    "admissionInfo" : "11月1日起開放索票，請於週一至週五上午 09:00 至下午 17:00，至中壢藝術館、桃園展演中心、桃園市政府文化局服務台索取，每人限索 2 張。票券數量有限，索完為止。\n\n※ 為配合政府防疫相關規定，入場前請於實體票券背面填寫實名制資料。造成不便，敬請見諒！",
    "admissionNumber" : "",
    "admissionDate" : "2021-11-01T09:00:00",
    "handicap" : "",
    "publishDate" : "2021/10/26 09:12 上午",
    "performanceDate" : [ "2021/12/12 07:30 下午~2021/12/12 09:05 下午" ],
    "pic" : [ "https://www.afmc.gov.tw/Upload/202110260912611ca84f0.png", "https://www.afmc.gov.tw/Upload/2021102609121659f6e20.png", "https://www.afmc.gov.tw/Upload/202110260912556add840.png" ],
    "hashCode" : "1996547612"
  }, {
    "troupeName" : "串音有限公司《我祝妳幸福》在桃園",
    "hallType" : "桃園展演中心",
    "hallSelect" : "展演廳",
    "performanceType" : "表演類",
    "performanceSelect" : "音樂",
    "title" : "串音有限公司《我祝妳幸福》在桃園",
    "content" : "全球疫情之際，人們被迫限行索居，甚至隔離別世，溫馨祝福的詞語及安寧靜心的旋律是迫切的需求與身心靈最療癒的陪伴。\n\n適逢令大家懷念與尊敬的鳳飛飛女士第一首成名曲「祝你幸福」問世50周年，作詞者同時也是催生鳳姐出演第一部電影「春寒」的劇本寫手林煌坤老師特此獻出畢生創作精選，並擔任整場引言說書人，以他超資深台灣流行音樂暢銷作詞人的身份，介紹除他以外，歷年為鳳姐演唱事業貢獻創作的其他詞曲作家的作品，由台灣與日本當代大大小小音樂舞蹈藝術家們聯手重新詮釋歌曲，並從桃園發表。\n\n一則緬懷鳳姐象徵她的福音返鄉探望同歡，二則敬邀在地人士同頻共振一起發聲為全球祈福，同時思考疫情之後，新的幸福是什麼？\n\n節目概念 : 致敬幕後英雄們 - 詞曲作家及基層工作人員等 \n上半場 - 獻給桃園 / 疫情最前線 / 鳳飛飛家鄉與粉絲 / 重溫舊時光\n下半場 - 獻給全球 / 疫情同戰線 / 多元融和全國與各民族 / 創新與共生\n\n★★演出介紹★★\n楓葉情                                 [林煌坤：詞＋駱明道：曲 ]\n溫暖的秋天                        [劉家昌：詞曲 ]\n心肝寶貝                            [羅大佑：曲＋李坤城/羅大佑：詞] \n相思爬上心底                   [馬飼野俊ㄧ：曲＋林煌坤：詞]\n好好愛我                            [ 曲：高中正義/李超群＋詞：林煌坤]\n我不能沒信心                   [ 邱慶彰：詞曲 ] \n祝你幸福                            [林家慶：曲＋林煌坤：詞 ]\n我是一片雲                        [瓊瑤：詞＋左宏元：曲]     \n奔向彩虹                            [瓊瑤：詞＋左宏元：曲]  \n沒有泥土哪有花               [林家慶：曲＋林煌坤：詞] \n又見溜溜的他                   [瓊瑤：詞＋左宏元：曲]    \n五月的花                            [劉家昌：曲＋ 林煌坤：詞]  \n我願                                     [鄭貴昶：詞曲]    \n涼啊涼                                [小蟲：詞曲]\n我的愛 我的夢 我的家   [黃怡：曲＋ 丁曉雯：詞 ]\n愛你在心口難開              [中文詞:黃河/ JERRY ALLISON/SONNY CURTIS] \n愛不是佔有                       [ 曲：筒美京平＋林煌坤：詞 ]\n掌聲響起                           [陳桂芬：詞＋陳進興：曲  ]    \n流水年華                           [常富喜雄：曲＋蔣榮伊：詞]\n我祝妳幸福                       [林煌坤：詞+ PEACE靖/李昀陵：曲]\n\n\n製作群\n\n製作人：李昀陵 | 行銷企劃總監：張肖龍 | 節目設計：李昀陵+林煌坤+丁曉雯 | 導演：樓恩奇 | 音樂總監：洪筠惠 | 編曲：洪筠惠+池田欣彌+劉旭明 | 舞蹈設計：山口貴繪 | 執行導演：王永慶｜現場導播：周正隆｜現場混音工程：毛琮文｜媒體公關：李珩 | 視覺溝通：張肖龍 | 舞台監督：王靖和 | 版權處理：戴克芳｜ | 燈光音響：捷韻實業｜攝影支援：法樂文化傳播｜\n\n說書人：林煌坤\n歌手：丁曉雯 | 王蘭榮 | 方寧 | 李昀陵 | 宋聖揚 | 韋喆Keril｜張博凱 | 賴佩霞 | PEACE靖\n舞者：山口貴繪+EXPG舞者\n鍵盤：洪筠惠 | 鼓：根石大輔 | Bass：池田欣彌 | 吉他：劉旭明 | \nSaxophone：彭國書\n\n主辦單位：串音有限公司、絲露思路\n\n協辦單位：中華好好說話，學會、愛夢悅股份有限公司",
    "performanceTimeInfo" : "原  8/21(日)   19:00-21:00  演出\n\n★★  因疫情延至  12/9(四) 19:30-21:30  演出    ★★",
    "url" : "https://fb.me/e/X12g27mm",
    "admissionWay" : "索票",
    "admissionInfo" : "索票優先邀請婦女族群與一線醫護清潔人員，以褒揚慰勞她們無私的辛勤奉獻。\n索票優先團體聯繫窗口 : 絲露思路 0938735777\nE-mail：iwishyouhappytw@gmail.com\n\n★★ 索票資訊 ★★\n1.  11/01 (一) 於「我祝妳幸福」在桃園臉書活動專頁開放實名登記索票\n2.  11/29 (一) 於桃園展演中心現場開放實名登記索票\n\n報到時間\n12/9 (四) 18:30-19:20\n\n現場開放實名補位時間\n12/9 (四) 19:00-19:30",
    "admissionNumber" : "",
    "admissionDate" : "2021-11-29T09:00:00",
    "handicap" : "",
    "publishDate" : "2021/06/24 11:34 上午",
    "performanceDate" : [ "2021/12/09 07:30 下午~2021/12/09 09:30 下午" ],
    "pic" : [ "https://www.afmc.gov.tw/Upload/20210722132877244c390.png", "https://www.afmc.gov.tw/Upload/202107221328326f8fff0.png", "https://www.afmc.gov.tw/Upload/2021072213285229dc430.png", "https://www.afmc.gov.tw/Upload/2021072613256958b0790.png" ],
    "hashCode" : "1120105941"
  }, {
    "troupeName" : "桃園市國樂團",
    "hallType" : "中壢藝術館",
    "hallSelect" : "音樂廳",
    "performanceType" : "表演類",
    "performanceSelect" : "音樂",
    "title" : "《桃園之星》2021桃園市國樂團器樂大賽",
    "content" : "桃園市國樂團以推廣國樂為首要任務，為正在學習國樂路上的青年學子們，提供展演的舞台與機會！桃市國本次將身為幕後推手，將別具演出風範的青年演奏家推上正式演出舞台。\n2021器樂大賽計畫在2021年初即展開熱烈的報名與選拔，於4月25日公開甄選青年演奏家，邀請國樂界具有影響力的音樂家擔任專業評審，共遴選出五位優秀演奏家，除了為優勝者提供豐厚獎金作為鼓勵外，也將於12月21日《桃園之星》2021桃園市國樂團器樂大賽與黃光佑指揮、桃園市國樂團同台演出。",
    "performanceTimeInfo" : "12/21(二) 19:30",
    "url" : "",
    "admissionWay" : "售票",
    "admissionInfo" : "OPENTIX售票：100",
    "admissionNumber" : "",
    "admissionDate" : "",
    "handicap" : "",
    "publishDate" : "2021/12/02 10:13 上午",
    "performanceDate" : [ "2021/12/21 07:30 下午~2021/12/21 09:30 下午" ],
    "pic" : [ "https://www.afmc.gov.tw/Upload/2021120210139075d2490.png" ],
    "hashCode" : "587874262"
  }, {
    "troupeName" : "風動室內樂團",
    "hallType" : "中壢藝術館",
    "hallSelect" : "音樂廳",
    "performanceType" : "表演類",
    "performanceSelect" : "音樂",
    "title" : "《無限》電影配樂音樂會: 風動室內樂團",
    "content" : "2020年，風動以《無限》線上音樂會，陪伴大家走過每個防疫的日子。今年，風動要用音樂帶來一點正能量，以堅強的陣容呈現《無限》電影配樂音樂會給所有粉絲。2021年12月，讓我們用震撼、感人的旋律上演一齣齣好戲，讓所有人都能帶著希望、一起勇敢前進。\n\n演出曲目：\n星際大戰/Star Wars Saga (From \"Star Wars\")\nBy: John Williams  Arr.: Johan de Meij\n－\n馴龍高手/How to Train Your Dragon (From \"How to Train Your Dragon\")\nBy: John Powell  Arr.: Ton van Grevenbroek\n－\n神鬼奇航3：世界的盡頭/At World's End (From \"Pirates of the Caribbean: At World's End\")\nBy: Hans Zimmer  Arr.: Erik Rozendom\n－\n「炎-LiSA」《鬼滅之刃劇場版：無限列車篇》主題曲/「炎-LiSA」劇場版「鬼滅の刃」無限列車編 主題歌 (From \"劇場版「鬼滅の刃」無限列車編\")\nBy: 梶浦 由記  Arr.: 今村 愛紀\n－\n神隱少女配樂精選/「千と千尋の神隠し」ハイライト (From \"千と千尋の神隠し\")\nBy: 久石 譲  Arr.: 遠藤 幸夫\n－\n功夫熊貓/Kung Fu Panda (From \"Kung Fu Panda\")\nBy: John Powell/Hans Zimmer  Arr.: Ludwig Hjortenhammar\n－\n《復仇者聯盟：終局之戰》配樂精選/Soundtrack Highlights from Avengers: Endgame (From \"Avengers: Endgame\")\nBy: Alan Silvestri  Arr.: Michael Brown\n－\n風之谷配樂精選/「風の谷のナウシカ」Highlights (From \"風の谷のナウシカ\")\nBy: 久石 譲  Arr.: 真島 俊夫\n\n（主辦單位保有調整演出曲目之權利）",
    "performanceTimeInfo" : "12/18(六)19:30",
    "url" : "https://tixfun.com/UTK0201_?PRODUCT_ID=N117JW1W",
    "admissionWay" : "售票",
    "admissionInfo" : "Tixfun售票系統: 500、700、900、1100、1300",
    "admissionNumber" : "",
    "admissionDate" : "",
    "handicap" : "",
    "publishDate" : "2021/11/16 04:56 下午",
    "performanceDate" : [ "2021/12/18 07:30 下午~2021/12/18 10:00 下午" ],
    "pic" : [ "https://www.afmc.gov.tw/Upload/202111161722074f5e230.png", "https://www.afmc.gov.tw/Upload/2021111617222697e6480.png", "https://www.afmc.gov.tw/Upload/202111161722182e005b0.png", "https://www.afmc.gov.tw/Upload/202111161723221242ee0.png", "https://www.afmc.gov.tw/Upload/202111161723831687250.png" ],
    "hashCode" : "1914900748"
  }, {
    "troupeName" : "國立臺灣戲曲學院",
    "hallType" : "桃園展演中心",
    "hallSelect" : "展演廳",
    "performanceType" : "表演類",
    "performanceSelect" : "舞蹈",
    "title" : "教育部新住民教育揚才計畫-新住民舞蹈比賽",
    "content" : "教育部長期關注新住民及其子女在臺生活相關發展，為深化新住民子女所兼具的發展優勢，運用其多元的語言學習環境、跨國文化的成長背景優勢，以適性揚才，協助「新住民」適應環境更能發展潛能，在國際競爭中脫穎而出。應於十二年國民基本教育課程綱要總綱，將新住民語文列為「語文」領域課程之一，以落實「成就每一個孩子」的願景、「尊重多元文化」之課程目標，提升國家整體競爭力。",
    "performanceTimeInfo" : "12月11日(六)13:00-17:00",
    "url" : "",
    "admissionWay" : "其他",
    "admissionInfo" : "不對外開放",
    "admissionNumber" : "",
    "admissionDate" : "",
    "handicap" : "",
    "publishDate" : "2021/11/19 04:26 下午",
    "performanceDate" : [ "2021/12/11 01:00 下午~2021/12/11 03:00 下午" ],
    "pic" : [ "https://www.afmc.gov.tw/Upload/202111191739096f630e0.png" ],
    "hashCode" : "1228821745"
  }, {
    "troupeName" : "果陀劇場 ",
    "hallType" : "桃園展演中心",
    "hallSelect" : "展演廳",
    "performanceType" : "表演類",
    "performanceSelect" : "戲劇",
    "title" : "果陀劇場《最後14堂星期二的課》",
    "content" : "《最後14堂星期二的課》\nMitch Albom's TUESDAYS WITH MORRIE By Jeffrey Hatcher and Mitch Albom\n\n「你跟你的心靈能夠和平相處嗎？」\n「生命只有一次，我想好好活著……」\n\n最富有生命力的真實故事、笑中帶淚\n值得您與生命中最重要的人一起觀賞\n\n國際知名導演        楊世彭\n國家文藝獎得主    金士傑  \n金獎演員                 卜學亮\n\n《最後14堂星期二的課》自2011年2月巡迴至今超過280場，突破25萬名劇迷熱烈喜愛與廻響，百餘位名人蒞臨看戲皆深受感動，十週年特別加演，絕對震撼心靈！\n改編自美國知名專欄作家Mitch Albom的同名暢銷小説《最後十四堂星期二的課》(英文名：Tuesdays with Morrie)，全球銷售超過50個版本、1700萬冊您絕對不可錯過的好戲：\n一本美妙的書，一個作者以靈魂訴說，關於心靈的故事—【洛杉磯時報】\n對死亡這門課來說是個非凡的貢獻--【波士頓環球報】\n生動捕捉到複雜生命背後的簡單純粹，既清晰又富有智慧的美麗故事。--【美國暢銷心靈作家史考特‧派克(M. Scott Peck,M.D.)】\n\n知名導演 瞿友寧：「非常喜歡金士傑老師在劇中靜態時候的畫面，氣氛很美，投影設計很棒，像是詩一般的畫，這是一齣要靜下心用心體會的戲，推薦給大家。 」\n\n\n您絕對不可錯過的好戲 《最後14堂星期二的課》\n感謝您陪我們走過的每一堂課...\n\n\n★故事大綱★\n體育專欄作家米奇(卜學亮 飾)，偶然從電視上看見大學時期對他期望最大的教授莫利(金士傑 飾)竟罹患了無藥可醫的「肌萎縮性脊髓側索硬化症」(簡稱ALS)。師生二人久別重逢，不畏懼「死亡」的教授以自己的生命為活教材，把自己最真實的生命經驗，教授給這位世故而冷漠、追求物質的學生，希望透過學生的記錄，把自己的生命歷程、生死的領悟記錄下來，兩人用了14個星期二的時間，展開一段幽默又觸動人心的生死對話......",
    "performanceTimeInfo" : "2022/04/30（六）19:30\n2022/05/01（日）14:30",
    "url" : "https://godot.org.tw/web/tuesday/",
    "admissionWay" : "售票",
    "admissionInfo" : "TixFun售票系統\n500/900/1400/1700/2000/2300/2600",
    "admissionNumber" : "",
    "admissionDate" : "",
    "handicap" : "",
    "publishDate" : "2021/10/21 04:52 下午",
    "performanceDate" : [ "2022/04/30 07:30 下午~2022/04/30 05:30 下午" ],
    "pic" : [ "https://www.afmc.gov.tw/Upload/20211021165228374a170.png", "https://www.afmc.gov.tw/Upload/2021102117169837c5440.png", "https://www.afmc.gov.tw/Upload/202110211657102fd8e30.png" ],
    "hashCode" : "1885041010"
  }, {
    "troupeName" : "福豐國中第五屆國樂班",
    "hallType" : "中壢藝術館",
    "hallSelect" : "音樂廳",
    "performanceType" : "表演類",
    "performanceSelect" : "音樂",
    "title" : "福豐國中第五屆國樂班畢業音樂會「午夜，鐘聲響」",
    "content" : "此場演出上半場將安排小型音樂劇場演出。劇情推至西元2059年，在疫情無止盡的肆虐下，表演藝術幾乎面臨絕跡，當口罩解禁的鐘聲響起，大家歡欣鼓舞脫下口罩，樂團終於加入管樂，讓音樂回歸最初完美的平衡，透過鄧名佑導演細膩的手法，孩子結合器樂演出有著生動的表演。下半場將由福豐國中國樂團帶來演出，曲目內容涵蓋合奏、協奏等演出型式，藉由音樂廳專業的演出空間，讓孩子們的音樂演出更臻完美。",
    "performanceTimeInfo" : "12/22(三)19:30",
    "url" : "",
    "admissionWay" : "索票",
    "admissionInfo" : "12/6於福豐國中警衛室及中壢藝術館開放索票，每人限索四張，索完為止",
    "admissionNumber" : "",
    "admissionDate" : "2021-12-06T09:00:00",
    "handicap" : "",
    "publishDate" : "2021/11/24 02:48 下午",
    "performanceDate" : [ "2021/12/22 07:30 下午~2021/12/22 09:30 下午" ],
    "pic" : [ "https://www.afmc.gov.tw/Upload/202111241448319d22050.png", "https://www.afmc.gov.tw/Upload/202111241448981f5cfb0.png", "https://www.afmc.gov.tw/Upload/202111241448570914c10.png", "https://www.afmc.gov.tw/Upload/2021112414480127d3200.png", "https://www.afmc.gov.tw/Upload/202111241448709482ca0.png", "https://www.afmc.gov.tw/Upload/202111241448657651a40.png" ],
    "hashCode" : "39654432"
  }, {
    "troupeName" : "九歌兒童劇團",
    "hallType" : "桃園展演中心",
    "hallSelect" : "展演廳",
    "performanceType" : "表演類",
    "performanceSelect" : "戲劇",
    "title" : "2021世界和平會兒童戲劇慈善公演「判官審石頭」",
    "content" : "捐款幫助受飢兒童的暑假餐費與愛心早餐。獲贈九歌兒童劇團「判官審石頭」入場券：快樂村裡賣油條的小六子，身上錢袋在市集被偷了，村民七嘴八舌幫倒忙，最後決定請判官大老爺來找出到底誰是小偷。",
    "performanceTimeInfo" : "12月12日(日)14:00",
    "url" : "",
    "admissionWay" : "其他",
    "admissionInfo" : "捐款贈票",
    "admissionNumber" : "",
    "admissionDate" : "",
    "handicap" : "",
    "publishDate" : "2021/11/19 04:30 下午",
    "performanceDate" : [ "2021/12/12 02:00 下午~2021/12/12 04:00 下午" ],
    "pic" : [ "https://www.afmc.gov.tw/Upload/202111191630575c0f4a0.png" ],
    "hashCode" : "1746718230"
  }, {
    "troupeName" : "陳明章",
    "hallType" : "A8藝文中心",
    "hallSelect" : "展覽空間",
    "performanceType" : "表演類",
    "performanceSelect" : "講座",
    "title" : "【那些年的臺灣音樂故事】",
    "content" : "配合「不簡單小故事」展覽，陳明章老師特別帶來那些年的臺灣好聲音；看台灣流行音樂的發展過程，如何從翻唱歌曲進展到創作歌曲，其中70年代的校園民歌扮演著極為重要的角色。一同聽聽過去文藝青年的耳畔迴音，如何從日常出發，結合詩文與大眾文化，寄託了一整個世代對於社會脈動的共同記憶。",
    "performanceTimeInfo" : "12/11 14:30-16:00",
    "url" : "http://www.a8artcenter.com.tw/signup.php?utm_source=afmc&utm_medium=event",
    "admissionWay" : "自由入場",
    "admissionInfo" : "請事先至A8藝文中心官方網站(http://www.a8artcenter.com.tw/signup.php?utm_source=afmc&utm_medium=event)報名，現場開放後補。",
    "admissionNumber" : "",
    "admissionDate" : "",
    "handicap" : "",
    "publishDate" : "2021/11/23 07:09 下午",
    "performanceDate" : [ "2021/12/11 02:30 下午~2021/12/11 04:00 下午" ],
    "pic" : [ "https://www.afmc.gov.tw/Upload/202111231909800bc3090.png" ],
    "hashCode" : "1404999224"
  }, {
    "troupeName" : "君涵樂坊",
    "hallType" : "中壢藝術館",
    "hallSelect" : "音樂廳",
    "performanceType" : "表演類",
    "performanceSelect" : "音樂",
    "title" : "君涵樂坊《台灣風情-從鄉土到現代》",
    "content" : "【台灣風情-從鄉土到現代】是以台灣各地美景進行深入瞭解，並由鄉土到現代透過專業的創作群對於各場音樂的編作，以傳統音樂之展現，注入現代意象之創作，重新詮釋台灣各地風情，並賦予新的風貌與生命。\n\n\uD83C\uDFB6\uD83C\uDFB6演出曲目：三生有幸、鵝鸞鼻之春、台灣民謠組曲、客家民謠聯奏、牧民新歌、阮若打開心內的門窗…",
    "performanceTimeInfo" : "9/3   14:30  ",
    "url" : "",
    "admissionWay" : "索票",
    "admissionInfo" : "索票入場",
    "admissionNumber" : "",
    "admissionDate" : "2022-08-03T09:00:00",
    "handicap" : "",
    "publishDate" : "2021/04/26 09:57 上午",
    "performanceDate" : [ "2022/09/03 02:30 下午~2022/09/03 04:00 下午" ],
    "pic" : [ "https://www.afmc.gov.tw/Upload/20210602165115861aef0.png" ],
    "hashCode" : "2017836508"
  }, {
    "troupeName" : "風雅頌古箏樂團、鳴響風室內樂團",
    "hallType" : "中壢藝術館",
    "hallSelect" : "音樂廳",
    "performanceType" : "表演類",
    "performanceSelect" : "音樂",
    "title" : "《邊疆．初見》",
    "content" : "邊疆濃郁的民族風格及地方色彩，勾勒出一幕幕動人的樂章。傳統絲竹樂器與雙大提琴的結合，呈現東西方樂器交融，展現演奏家們的重奏協調性與技術性，時而雄厚渾長、時而歡快跳躍、時而粗曠奔放、時而柔緩情深，讓我們一起探索樂章的最深處，若如初見。\n\n曲目/《春天》《江雪》《燕子》《塔里木旋回舞曲》《草原升起不落的太陽》《草原英雄小姊妹》《土耳其異想曲》《天山盛會》《七彩湖畔》《絲路駝鈴》。",
    "performanceTimeInfo" : "2022/1/16 (日) 14:30",
    "url" : "https://www.opentix.life/event/1463093566641065987",
    "admissionWay" : "售票",
    "admissionInfo" : "OPENTIX售票: 300、500",
    "admissionNumber" : "",
    "admissionDate" : "",
    "handicap" : "",
    "publishDate" : "2021/12/07 04:48 下午",
    "performanceDate" : [ "2022/01/16 02:30 下午~2022/01/16 05:00 下午" ],
    "pic" : [ "https://www.afmc.gov.tw/Upload/2021120716487364382a0.png" ],
    "hashCode" : "307448544"
  }, {
    "troupeName" : "TMJO 臺北都會爵士大樂隊指揮/烏野薫",
    "hallType" : "A8藝文中心",
    "hallSelect" : "展覽空間",
    "performanceType" : "表演類",
    "performanceSelect" : "音樂",
    "title" : "【爵士狂歡派對】",
    "content" : "臺北爵士大樂隊都會團（TMJO），由薩克斯風演奏家李承育擔任音樂總監。希望帶來更為豐富多元的演出，持續散發爵士樂的熱情和奔放，讓大眾在享受爵士樂美好的同時，也隨之一同搖擺、起舞。在年末之時，希望用爵士的搖擺歡慶一年的辛苦收穫，也分享音樂的美好與喜悅。",
    "performanceTimeInfo" : "12/12 14:30-16:00",
    "url" : "http://www.a8artcenter.com.tw/signup.php?utm_source=afmc&utm_medium=event",
    "admissionWay" : "自由入場",
    "admissionInfo" : "請事先至A8藝文中心官方網站(http://www.a8artcenter.com.tw/signup.php?utm_source=afmc&utm_medium=event)報名，現場開放後補。",
    "admissionNumber" : "",
    "admissionDate" : "",
    "handicap" : "",
    "publishDate" : "2021/11/23 07:26 下午",
    "performanceDate" : [ "2021/12/12 02:30 下午~2021/12/12 04:00 下午" ],
    "pic" : [ "https://www.afmc.gov.tw/Upload/202111231929756760400.png" ],
    "hashCode" : "472996546"
  }, {
    "troupeName" : "自強國中第十屆美術班",
    "hallType" : "中壢藝術館",
    "hallSelect" : "第1展覽室",
    "performanceType" : "展覽類",
    "performanceSelect" : "學校畢業展",
    "title" : "自強國中第十屆美術班畢業美展－「十藝˙拾憶」",
    "content" : "我們是一顆顆藝術的種子，經過三年來的滋養而萌芽，我們對藝術一見傾心，每一件作品都是努力耕耘的軌跡，細細訴說著成長的故事！我們透過藝術，開發無限的潛能，透過創意，開創精彩的未來，揮灑彩筆，盡情在生活風景中描繪那浮光掠影、驚鴻一瞥的美，收藏那難以言說的感動！\n誠摯的邀請您與我們共享藝術的果實，您的鼓勵與指導，將是我們在藝術藍海遨遊的最佳動力。",
    "performanceTimeInfo" : "12/10(五)-12/19(日)9:00-17:00\n每週一休展",
    "url" : "",
    "admissionWay" : "自由入場",
    "admissionInfo" : "",
    "admissionNumber" : "",
    "admissionDate" : "",
    "handicap" : "",
    "publishDate" : "2021/12/02 10:20 上午",
    "performanceDate" : [ "2021/12/10 09:00 上午~2021/12/10 05:00 下午", "2021/12/11 09:00 上午~2021/12/11 05:00 下午", "2021/12/12 09:00 上午~2021/12/12 05:00 下午", "2021/12/13 09:00 上午~2021/12/13 05:00 下午", "2021/12/14 09:00 上午~2021/12/14 05:00 下午", "2021/12/15 09:00 上午~2021/12/15 05:00 下午", "2021/12/16 09:00 上午~2021/12/16 05:00 下午", "2021/12/17 09:00 上午~2021/12/17 05:00 下午", "2021/12/18 09:00 上午~2021/12/18 05:00 下午", "2021/12/19 09:00 上午~2021/12/19 05:00 下午" ],
    "pic" : [ "https://www.afmc.gov.tw/Upload/202112021020610223010.png", "https://www.afmc.gov.tw/Upload/2021120210201083a4b80.png", "https://www.afmc.gov.tw/Upload/2021120210200000c5390.png" ],
    "hashCode" : "991494186"
  }, {
    "troupeName" : "果陀劇場",
    "hallType" : "桃園展演中心",
    "hallSelect" : "展演廳",
    "performanceType" : "表演類",
    "performanceSelect" : "戲劇",
    "title" : "果陀劇場《生命中最美好的5分鐘》",
    "content" : "果陀劇場 舞動奇蹟音樂劇\n穿梭時空 讓遺憾出現奇蹟?\n關於遺憾，如果你有一首歌的時間…\n熱愛音樂的粗心死神誤殺了命不該絕的John，為了彌補疏失，死神答應他「穿越時空改變錯誤」的願望。當特定的音樂響起，只有短短的五分鐘，John穿梭時空遇見與自己相像的中學生！人生真的能重來？\n\n關於人生，愛讓一切有意義…\n一封前女友捎來的喜帖，喚起John深埋難解的心結與自責…如何再次面對錯過的真愛？一次次的穿越與相處，John實在難以開口告訴青年：你所期盼的未來，你我的人生、夢想，會是一連串的錯誤與徒勞….\n\n夢想 愛情 現實\n用音樂治癒生命缺憾\n導演 梁志民    音樂總監 陳國華\n「筋斗云創劇本創投平台第三屆獲選作品」    編劇 王慕天\n郭靜、楊奇煜、蔡旻佑    聯合主演\n動感喜劇天王   唐從聖    特別主演\n暨音樂劇菁英    聯合演出\n\n果陀劇場官方網站：http://www.godot.org.tw\n果陀劇場 FACEBOOK粉絲團：http://www.facebook.com/godotfans\n果陀劇場Instagram官方帳號：IG搜尋@godot_theatre\n果陀劇場官方LINE：LINE搜尋@godot",
    "performanceTimeInfo" : "2021/05/29(六)19:30 延期至 2022/08/27(六) 19:30\n2021/05/30(日)14:30 延期至 2022/08/28(日) 14:30\n\n全長135分鐘，不含中場休息15分鐘。",
    "url" : "https://www.youtube.com/watch?v=EjVAAihMzgo",
    "admissionWay" : "售票",
    "admissionInfo" : "TixFun售票網：400、700、1000、1500、1800、2200、2500\n\n【延期公告】《生命中最美好的5分鐘》5/29-30桃園展演中心 延期演出。造成您的不便，敬請見諒！\n \n配合5/11中央防疫建議，果陀劇場與場館方及各演工作人員努力協調後，場次更換如下：\n \n桃園展演中心\n2021/05/29(六)19:30 延期至 2022/08/27(六) 19:30\n2021/05/30(日)14:30 延期至 2022/08/28(日) 14:30\n \n已購票觀眾持原票券入座新場次，不需換票。\n若持票觀眾不便觀賞新的場次，自公告日起至2021/6/8前洽原購票單位辦理全額退票。\n \n【退票處理辦法】\n一、向果陀劇場傳真購票之觀眾：\n請於 2021/6/8前聯繫果陀劇場 02-87721867辦理（週一至週五 10:00AM～18:00PM）。\n \n二、向TixFun售票系統購票之觀眾(含電子票超商購票/取票)：\n1.電子票券或尚未於ibon取票者，請於2021/6/8前可透過Tixfun售票網或Tixfun APP，會員服務中訂單查詢，進行退票，款項將退刷至原購票之信用卡。您也可以選擇將退票款【轉成贊助款】，將您的票款贊助給果陀劇場，協助台灣表演藝術團隊度過疫情的艱困時期。\n \n2.已經於ibon取票： \n★現金購票者請附上實體票正本、退款帳戶影本，郵寄至以下地址，以退款到您的帳戶。\n★刷卡購票者請附上實體票正本郵寄至以下地址，款項將退刷至原購票之信用卡。\n請於2021/6/8前掛號郵寄至「106台北市大安區信義路四段6號15樓之12，双融藝股份有限公司收」，以退換票郵件寄送日郵戳為憑。\n \n三、GOMAJI管道購票之觀眾：\n請於 2021/6/8前洽詢GOMAJI客服專線(02)2711-1758（週一至週五 9:00AM ~ 18:00PM）。\n \n為維護所有觀眾以及演工作人員之健康安全，因此決策公告如上，期望各界朋友體諒，給予果陀劇場支持與鼓勵，防疫期間，我們將持續為演出做準備，期盼疫情早日結束，大家平安健康、我們劇場見。\n \n有任何疑問，請洽果陀劇場：02-87721867或TixFun售票系統客服中心：02-27073053（週一至週五 10:00AM～18:00PM）。",
    "admissionNumber" : "",
    "admissionDate" : "",
    "handicap" : "",
    "publishDate" : "2021/03/30 05:29 下午",
    "performanceDate" : [ "2022/08/27 07:30 下午~2022/08/27 05:00 下午" ],
    "pic" : [ "https://www.afmc.gov.tw/Upload/202103301729538cb64e0.png", "https://www.afmc.gov.tw/Upload/202103301729231c8bc50.png", "https://www.afmc.gov.tw/Upload/2021033017290922ffd60.png" ],
    "hashCode" : "1852305864"
  }, {
    "troupeName" : "桃園交響管樂團",
    "hallType" : "桃園展演中心",
    "hallSelect" : "展演廳",
    "performanceType" : "表演類",
    "performanceSelect" : "音樂",
    "title" : "桃園交響管樂團《格列佛勇闖綠野仙蹤》",
    "content" : "本場音樂會特別選擇了兩部經典之作《格列佛遊記》(小說)以及《綠野仙蹤》(童話故事)為故事主軸，藉由音樂引導促使觀眾激發情緒的張力，以及劇團演故事的視覺串聯，達到情境的豐富想像力，其目的為利用藝術將閱讀升級、利用藝術將感受強化。\n\n期盼將這些經典的音樂及文學在親子之間搭起新的共鳴，親子間彼此分享音樂及故事所帶來的想像及畫面，更希望能激發是一場有趣又溫馨的親子音樂會。\n\n本場音樂會之焦點專注於音樂靈魂賦予故事生命力，樂團演奏主導故事、邀請萬花筒劇團，帶領觀眾進入故事的世界，節目內容為趨近孩童們喜歡的旋律風格與頻率，所演出之曲目精心挑選，節目中透過劇團的故事帶入樂器、作曲家及曲目背景的介紹，以平易近人的方式貼近觀眾。\n\n故事大綱：\n勇敢的格列佛偶然闖進綠野仙蹤的小島！從悲傷的稻草人得知，桃樂絲被西方女巫抓走，甚至還偷走島上快樂泉源的音樂魔法書！見義勇為的格列佛決定一起冒險救出桃樂絲！到底能不能成功打敗女巫，島上的精靈及動物們會不會奮力相挺呢？讓我們一起跟著冒險去吧！\n\n※演出曲目\n1. Gulliver’s Travels by Bert Appermont\n2. Clarinet Candy by Leroy Anderson\n3. L’Apprenti Sorcier by Paul Dukas\n4. Le Carnaval des Animaux arr. by Yo Goto\n5. The Carnival of the Animals arr. by Groffrey Brand\n6. A Trumpeter’s Lullaby by Leroy Anderson\n7. The Typewriter by Leroy Anderson\n8. The Wizard of Oz Medley by James Barnes",
    "performanceTimeInfo" : "12/18(六)   15:00\n\n\n",
    "url" : "",
    "admissionWay" : "售票",
    "admissionInfo" : "TixFun售票：300、500、800",
    "admissionNumber" : "",
    "admissionDate" : "",
    "handicap" : "",
    "publishDate" : "2021/11/08 10:55 上午",
    "performanceDate" : [ "2021/12/18 03:00 下午~2021/12/18 05:30 下午" ],
    "pic" : [ "https://www.afmc.gov.tw/Upload/2021110811017624732d0.png", "https://www.afmc.gov.tw/Upload/202111081059953474ba0.png", "https://www.afmc.gov.tw/Upload/202111081059702ffa080.png", "https://www.afmc.gov.tw/Upload/202111081108539afc610.png" ],
    "hashCode" : "1726718638"
  }, {
    "troupeName" : "銀河谷音劇團",
    "hallType" : "中壢藝術館",
    "hallSelect" : "音樂廳",
    "performanceType" : "表演類",
    "performanceSelect" : "親子",
    "title" : "得益寶股份有限公司「超人力霸王傑特舞台劇-保衛戰In Taiwan」",
    "content" : "『如果還有繼續戰鬥的信念…如果還想要守護這個星球，請呼喊我的名字！我的名字是…超人力霸王傑洛！』\n這是屬於〈超人力霸王傑特〉、〈超人力霸王傑洛〉、〈超人力霸王捷德〉以及〈特空機1號賽文加〉與地球防衛軍在台灣成立支部，共同守護台灣和平的故事。\n地球防衛軍台灣支部在訓練時，怪獸們悄悄現身台灣，強大攻擊力的怪獸讓大家無計可施！「不放棄戰鬥」是超人力霸王的信念，邀請孩子前來聲援，給戰士們力量、合力擊敗怪獸！",
    "performanceTimeInfo" : "12/26(日)13:30、16:30各1場",
    "url" : "",
    "admissionWay" : "售票",
    "admissionInfo" : "年代售票：400、500、600、800、1000、1200、1500",
    "admissionNumber" : "",
    "admissionDate" : "",
    "handicap" : "",
    "publishDate" : "2021/11/24 02:59 下午",
    "performanceDate" : [ "2021/12/26 01:30 下午~2021/12/26 03:00 下午", "2021/12/26 04:30 下午~2021/12/26 06:00 下午" ],
    "pic" : [ "https://www.afmc.gov.tw/Upload/20211124150098599aca0.png", "https://www.afmc.gov.tw/Upload/202111241500734439e90.png" ],
    "hashCode" : "1889141755"
  }, {
    "troupeName" : "心心南管樂坊、Voco Novo爵諾歌手、歐開合唱團",
    "hallType" : "中壢藝術館",
    "hallSelect" : "音樂廳",
    "performanceType" : "表演類",
    "performanceSelect" : "音樂",
    "title" : "2021桃園合唱藝術節開幕音樂會-跨界人聲(阿卡貝拉)之夜",
    "content" : "開幕音樂會以「跨界人聲」為主題，邀請「心心南管樂坊」王心心老師與「Voco Novo爵諾歌手帶來結合人聲、詩詞、南管的《人聲・南管・蝶戀花》選粹，阿卡貝拉天團「歐開合唱團」更將帶來爵士風格的原民古調，「2021桃園合唱藝術節阿卡貝拉大賽」冠軍團隊也將共同演繹，帶來一場別開生面的跨界人聲之夜。",
    "performanceTimeInfo" : "12/11(六)19:30\n",
    "url" : "https://vfty.org/concert-open",
    "admissionWay" : "索票",
    "admissionInfo" : "11月1日起開放索票，請於週一至週五上午 09:00 至下午 17:00，至中壢藝術館、桃園展演中心、桃園市政府文化局服務台索取，每人限索 2 張。票券數量有限，索完為止。\n※ 為配合政府防疫相關規定，入場前請於實體票券背面填寫實名制資料。造成不便，敬請見諒！",
    "admissionNumber" : "",
    "admissionDate" : "2021-11-01T09:00:00",
    "handicap" : "",
    "publishDate" : "2021/10/26 09:00 上午",
    "performanceDate" : [ "2021/12/11 07:30 下午~2021/12/11 09:10 下午" ],
    "pic" : [ "https://www.afmc.gov.tw/Upload/202110260900405367da0.png", "https://www.afmc.gov.tw/Upload/20211026090012341d3a0.png", "https://www.afmc.gov.tw/Upload/2021102609009079c1e40.png" ],
    "hashCode" : "57759122"
  }, {
    "troupeName" : "風潮音樂國際股份有限公司",
    "hallType" : "桃園展演中心",
    "hallSelect" : "展演廳",
    "performanceType" : "表演類",
    "performanceSelect" : "音樂",
    "title" : "【演出延期】風潮音樂國際股份有限公司－愛唱歌2021親子演唱會《瑞比和安弟的樹洞狂想》",
    "content" : "令上萬名大小觀眾感動及回味的「愛唱歌 2021 親子演唱會《瑞比和安弟的樹洞狂想》」，今年暑假強勢回歸！一靜一動的最佳拍檔「小兔瑞比」和「螞蟻安弟」，將與路途中遇上的動物朋友們，帶領全場一起Ｋ歌歡唱！\n\n親子音樂界人氣天團「謝欣芷的愛唱歌劇場」邀請大家加入這一趟充滿幸福與歡笑的音樂奇幻之旅！表演絕無冷場的親子演唱會，串聯超過15首膾炙人口的原創兒歌，讓大小觀眾們一首又一首唱個過癮！100分鐘絕對好看、好聽又好唱！",
    "performanceTimeInfo" : "原110年07月31日(六)  10:30、14:30\n\n延期至111年7月16日(六)  10:30、14:30\n",
    "url" : "https://ticket.com.tw/application/UTK02/UTK0201_.aspx?PRODUCT_ID=N189Z6LV",
    "admissionWay" : "售票",
    "admissionInfo" : "售票網站：年代售票 \n票價：1300 / 1100 / 900 / 700 / 500\n\n★★由於目前全國仍處於三級警戒，為確保每位大小觀眾與全體人員的健康，我們很遺憾地決定，愛唱歌2021親子演唱會《瑞比和安弟的樹洞狂想》將延期，謝謝大家一直以來對欣芷與愛唱歌團隊的支持與鼓勵！ \n\n 相關場次異動如下： \n\n【桃園場】原07/31 演出延期                   〔★★延期至111年7月16日★★〕\n♦ 第三波退票期限（僅適用桃園場）：\n並把握第二波退票期限（即日起至110年8月9日截止），再次感謝您們一直以來對欣芷與愛唱歌團隊的支持與鼓勵！ 郵寄辦理者以郵戳為憑。",
    "admissionNumber" : "",
    "admissionDate" : "",
    "handicap" : "",
    "publishDate" : "2021/05/17 03:51 下午",
    "performanceDate" : [ "2022/07/14 10:30 上午~2022/07/14 04:10 下午", "2022/07/15 10:30 上午~2022/07/15 04:10 下午", "2022/07/16 10:30 上午~2022/07/16 04:10 下午" ],
    "pic" : [ "https://www.afmc.gov.tw/Upload/202106231529036181120.png", "https://www.afmc.gov.tw/Upload/2021062315224865a42d0.png" ],
    "hashCode" : "1380519301"
  } ]
}